googletrans/__init__.py
googletrans/client.py
googletrans/constants.py
googletrans/gtoken.py
googletrans/models.py
googletrans/urls.py
googletrans/utils.py
googletrans_mxloli_ver-4.0.0.2.dist-info/LICENSE
googletrans_mxloli_ver-4.0.0.2.dist-info/METADATA
googletrans_mxloli_ver-4.0.0.2.dist-info/WHEEL
googletrans_mxloli_ver-4.0.0.2.dist-info/top_level.txt
googletrans_mxloli_ver-4.0.0.2.dist-info/RECORD
